{
  "wikidataId": "Q106625550",
  "name": "Corem Property Group",
  "description": "Corem Property Group är ett svenskt fastighetsbolag.",
  "reportingPeriods": [
    {
      "startDate": "2023-01-01T00:00:00.000Z",
      "endDate": "2023-12-31T00:00:00.000Z",
      "reportURL": "https://mb.cision.com/Main/9683/3953689/2701094.pdf",
      "economy": {
        "turnover": null,
        "employees": {
          "value": 309,
          "unit": null
        }
      },
      "emissions": {
        "scope1": {
          "total": 473,
          "unit": "tCO2e"
        },
        "scope2": {
          "lb": 10790,
          "mb": 4081,
          "unknown": null,
          "unit": "tCO2e",
          "calculatedTotalEmissions": 4081
        },
        "scope3": {
          "statedTotalEmissions": {
            "total": 62722,
            "unit": "tCO2e"
          },
          "categories": [
            {
              "category": 2,
              "total": 6905,
              "unit": "tCO2e"
            },
            {
              "category": 3,
              "total": 1139,
              "unit": "tCO2e"
            },
            {
              "category": 6,
              "total": 135,
              "unit": "tCO2e"
            },
            {
              "category": 6,
              "total": 391,
              "unit": "tCO2e"
            },
            {
              "category": 7,
              "total": 334,
              "unit": "tCO2e"
            },
            {
              "category": 13,
              "total": 28511,
              "unit": "tCO2e"
            }
          ],
          "calculatedTotalEmissions": 62722
        },
        "biogenicEmissions": null,
        "scope1And2": null,
        "statedTotalEmissions": {
          "total": 67276,
          "unit": "tCO2e"
        }
      }
    }
  ],
  "industry": {
    "industryGics": {
      "sectorCode": "60",
      "groupCode": "6010",
      "industryCode": "601010",
      "subIndustryCode": "60101010"
    }
  }
}