{
  "wikidataId": "Q2723182",
  "name": "Betsson",
  "description": "Betsson är ett företag som bedriver spelverksamhet över internet via dotterbolag. Företaget har sitt huvudkontor i Stockholm och är noterat på Nasdaq Stockholm Large Cap. Betsson har kontor i flera länder, inklusive Sverige, Malta och Gibraltar. Företaget erbjuder en mängd olika spelprodukter och tjänster, inklusive kasinospel, sportspel och poker.",
  "reportingPeriods": [
    {
      "startDate": "2023-01-01T00:00:00.000Z",
      "endDate": "2023-12-31T00:00:00.000Z",
      "reportURL": "https://www.betssonab.com/sites/default/files/pr/202404035951-1.pdf",
      "economy": {
        "turnover": {
          "value": 948200000,
          "currency": "EUR"
        },
        "employees": {
          "value": 2103,
          "unit": null
        }
      },
      "emissions": {
        "scope1": {
          "total": 224,
          "unit": "tCO2e"
        },
        "scope2": {
          "lb": 848,
          "mb": 1027,
          "unknown": null,
          "unit": "tCO2e",
          "calculatedTotalEmissions": 1027
        },
        "scope3": {
          "categories": [],
          "calculatedTotalEmissions": 0
        },
        "biogenicEmissions": null,
        "scope1And2": null,
        "statedTotalEmissions": {
          "total": 7334,
          "unit": "tCO2e"
        }
      }
    }
  ],
  "industry": {
    "industryGics": {
      "sectorCode": "25",
      "groupCode": "2530",
      "industryCode": "253010",
      "subIndustryCode": "25301010"
    }
  }
}