{
  "wikidataId": "Q56300749",
  "name": "HANZA",
  "description": "HANZA är ett globalt företag inom tillverkningsindustrin som kombinerar produktutveckling och rådgivning med egna fabriker i regionala kluster. Företaget erbjuder ett brett utbud av tillverkningsteknologier och fokuserar på att effektivisera leveranskedjor för sina kunder.",
  "reportingPeriods": [
    {
      "startDate": "2023-01-01T00:00:00.000Z",
      "endDate": "2023-12-31T00:00:00.000Z",
      "reportURL": null,
      "economy": {
        "turnover": {
          "value": 4143000000,
          "currency": "SEK"
        },
        "employees": {
          "value": 2001,
          "unit": "Average"
        }
      },
      "emissions": {
        "scope1": {
          "total": 1538,
          "unit": "tCO2e"
        },
        "scope2": {
          "lb": 0,
          "mb": 9449,
          "unknown": 0,
          "unit": "tCO2e",
          "calculatedTotalEmissions": 9449
        },
        "scope3": {
          "statedTotalEmissions": {
            "total": 0,
            "unit": "tCO2e"
          },
          "categories": [
            {
              "category": 16,
              "total": 0,
              "unit": "tCO2e"
            }
          ],
          "calculatedTotalEmissions": 0
        },
        "biogenicEmissions": null,
        "scope1And2": null,
        "statedTotalEmissions": {
          "total": 10987,
          "unit": "tCO2e"
        }
      }
    },
    {
      "startDate": "2022-01-01T00:00:00.000Z",
      "endDate": "2022-12-31T00:00:00.000Z",
      "reportURL": null,
      "economy": {
        "turnover": {
          "value": 3549000000,
          "currency": "SEK"
        },
        "employees": {
          "value": 1999,
          "unit": "FTE"
        }
      },
      "emissions": {
        "scope1": {
          "total": 193,
          "unit": "tCO2e"
        },
        "scope2": {
          "lb": 15150,
          "mb": 15150,
          "unknown": 0,
          "unit": "tCO2e",
          "calculatedTotalEmissions": 15150
        },
        "scope3": {
          "statedTotalEmissions": {
            "total": 0,
            "unit": "tCO2e"
          },
          "categories": [
            {
              "category": 16,
              "total": 0,
              "unit": "tCO2e"
            }
          ],
          "calculatedTotalEmissions": 0
        },
        "biogenicEmissions": null,
        "scope1And2": null,
        "statedTotalEmissions": {
          "total": 15343,
          "unit": "tCO2e"
        }
      }
    },
    {
      "startDate": "2021-01-01T00:00:00.000Z",
      "endDate": "2021-12-31T00:00:00.000Z",
      "reportURL": null,
      "economy": {
        "turnover": {
          "value": 2515000000,
          "currency": "SEK"
        },
        "employees": {
          "value": 1999,
          "unit": "FTE"
        }
      },
      "emissions": {
        "scope1": {
          "total": 122,
          "unit": "tCO2e"
        },
        "scope2": {
          "lb": 16139,
          "mb": 16139,
          "unknown": 0,
          "unit": "tCO2e",
          "calculatedTotalEmissions": 16139
        },
        "scope3": {
          "statedTotalEmissions": {
            "total": 0,
            "unit": "tCO2e"
          },
          "categories": [
            {
              "category": 16,
              "total": 0,
              "unit": "tCO2e"
            }
          ],
          "calculatedTotalEmissions": 0
        },
        "biogenicEmissions": null,
        "scope1And2": null,
        "statedTotalEmissions": {
          "total": 16261,
          "unit": "tCO2e"
        }
      }
    },
    {
      "startDate": "2020-01-01T00:00:00.000Z",
      "endDate": "2020-12-31T00:00:00.000Z",
      "reportURL": null,
      "economy": {
        "turnover": {
          "value": 2156000000,
          "currency": "SEK"
        },
        "employees": {
          "value": 1999,
          "unit": "FTE"
        }
      },
      "emissions": {}
    },
    {
      "startDate": "2019-01-01T00:00:00.000Z",
      "endDate": "2019-12-31T00:00:00.000Z",
      "reportURL": null,
      "economy": {
        "turnover": {
          "value": 2068000000,
          "currency": "SEK"
        },
        "employees": {
          "value": 1999,
          "unit": "FTE"
        }
      },
      "emissions": {}
    }
  ],
  "industry": {
    "industryGics": {
      "sectorCode": "45",
      "groupCode": "4520",
      "industryCode": "452030",
      "subIndustryCode": "45203020"
    }
  }
}